README.md
setup.py
shopline/__init__.py
shopline/api.py
shopline/comm/__init__.py
shopline/comm/comm.py
shopline/comm/exceptions.py
shopline/customer/__init__.py
shopline/customer/customer.py
shopline/orders/__init__.py
shopline/orders/order.py
shopline/product/__init__.py
shopline/product/addon_product.py
shopline/product/gift.py
shopline/product/product.py
shopline_sdk.egg-info/PKG-INFO
shopline_sdk.egg-info/SOURCES.txt
shopline_sdk.egg-info/dependency_links.txt
shopline_sdk.egg-info/requires.txt
shopline_sdk.egg-info/top_level.txt
shopline_sdk.egg-info/zip-safe
tests/__init__.py
tests/test_comm.py
tests/test_customer.py
tests/test_order.py
tests/test_product.py